{"Title":"Prince of Persia: The Sands of Time","Year":"2010","Rated":"PG-13","Released":"28 May 2010","Runtime":"116 min","Genre":"Action, Adventure, Fantasy","Director":"Mike Newell","Writer":"Boaz Yakin (screenplay), Doug Miro (screenplay), Carlo Bernard (screenplay), Jordan Mechner (screen story), Jordan Mechner (video game series \"Prince of Persia\")","Actors":"Jake Gyllenhaal, Gemma Arterton, Ben Kingsley, Alfred Molina","Plot":"Set in the mystical lands of Persia, a rogue prince and a mysterious princess race against dark forces to safeguard an ancient dagger capable of releasing the Sands of Time -- a gift from the gods that can reverse time and allow its possessor to rule the world.","Language":"English","Country":"USA","Awards":"9 nominations.","Poster":"http://ia.media-imdb.com/images/M/MV5BMTMwNDg0NzcyMV5BMl5BanBnXkFtZTcwNjg4MjQyMw@@._V1_SX300.jpg","Metascore":"50","imdbRating":"6.6","imdbVotes":"217,059","imdbID":"tt0473075","Type":"movie","Response":"True"}